{"dependencies":[{"name":"./internal/_curry2","loc":{"line":1,"column":20}},{"name":"./mergeDeepWithKey","loc":{"line":2,"column":29}}],"generated":{"js":"\"use strict\";\n\nObject.defineProperty(exports, \"__esModule\", {\n  value: true\n});\n\nvar _curry = require(\"./internal/_curry2\");\n\nvar _curry3 = _interopRequireDefault(_curry);\n\nvar _mergeDeepWithKey = require(\"./mergeDeepWithKey\");\n\nvar _mergeDeepWithKey2 = _interopRequireDefault(_mergeDeepWithKey);\n\nfunction _interopRequireDefault(obj) { return obj && obj.__esModule ? obj : { default: obj }; }\n\n/**\n * Creates a new object with the own properties of the first object merged with\n * the own properties of the second object. If a key exists in both objects:\n * - and both values are objects, the two values will be recursively merged\n * - otherwise the value from the first object will be used.\n *\n * @func\n * @memberOf R\n * @since v0.24.0\n * @category Object\n * @sig {a} -> {a} -> {a}\n * @param {Object} lObj\n * @param {Object} rObj\n * @return {Object}\n * @see R.merge, R.mergeDeepRight, R.mergeDeepWith, R.mergeDeepWithKey\n * @example\n *\n *      R.mergeDeepLeft({ name: 'fred', age: 10, contact: { email: 'moo@example.com' }},\n *                      { age: 40, contact: { email: 'baa@example.com' }});\n *      //=> { name: 'fred', age: 10, contact: { email: 'moo@example.com' }}\n */\nvar mergeDeepLeft = /*#__PURE__*/(0, _curry3.default)(function mergeDeepLeft(lObj, rObj) {\n  return (0, _mergeDeepWithKey2.default)(function (k, lVal, rVal) {\n    return lVal;\n  }, lObj, rObj);\n});\nexports.default = mergeDeepLeft;"},"hash":"18e870543d81a0d81f927f65dd1e5b0a"}