{"dependencies":[{"name":"./internal/_curry2","loc":{"line":1,"column":20}}],"generated":{"js":"\"use strict\";\n\nObject.defineProperty(exports, \"__esModule\", {\n  value: true\n});\n\nvar _curry = require(\"./internal/_curry2\");\n\nvar _curry3 = _interopRequireDefault(_curry);\n\nfunction _interopRequireDefault(obj) { return obj && obj.__esModule ? obj : { default: obj }; }\n\n/**\n * Acts as multiple `prop`: array of keys in, array of values out. Preserves\n * order.\n *\n * @func\n * @memberOf R\n * @since v0.1.0\n * @category Object\n * @sig [k] -> {k: v} -> [v]\n * @param {Array} ps The property names to fetch\n * @param {Object} obj The object to query\n * @return {Array} The corresponding values or partially applied function.\n * @example\n *\n *      R.props(['x', 'y'], {x: 1, y: 2}); //=> [1, 2]\n *      R.props(['c', 'a', 'b'], {b: 2, a: 1}); //=> [undefined, 1, 2]\n *\n *      var fullName = R.compose(R.join(' '), R.props(['first', 'last']));\n *      fullName({last: 'Bullet-Tooth', age: 33, first: 'Tony'}); //=> 'Tony Bullet-Tooth'\n */\nvar props = /*#__PURE__*/(0, _curry3.default)(function props(ps, obj) {\n  var len = ps.length;\n  var out = [];\n  var idx = 0;\n\n  while (idx < len) {\n    out[idx] = obj[ps[idx]];\n    idx += 1;\n  }\n\n  return out;\n});\nexports.default = props;"},"hash":"3e3f41d317ab6ef83adb4217a0eaba90"}